MANIFEST.in
setup.py
bootstrap_email/__init__.py
bootstrap_email/static/bootstrap-email.css
bootstrap_email/static/bootstrap-email.min.css
bootstrap_email/templatetags/__init__.py
bootstrap_email/templatetags/bootstrap_email.py
django_bootstrap_email.egg-info/PKG-INFO
django_bootstrap_email.egg-info/SOURCES.txt
django_bootstrap_email.egg-info/dependency_links.txt
django_bootstrap_email.egg-info/top_level.txt