Metadata-Version: 1.1
Name: django-bootstrap-email
Version: 0.0.1
Summary: Bootstrap e-mail support for Django projects
Home-page: https://github.com/kpekarov/django-bootstrap-email
Author: Kirill Pekarov
Author-email: kpekarov@gmail.com
License: Apache License 2.0
Platform: UNKNOWN
Classifier: Development Status :: 4 - Beta
Classifier: Intended Audience :: Developers
Classifier: License :: OSI Approved :: Apache Software License
Classifier: Programming Language :: Python
Classifier: Operating System :: OS Independent
Classifier: Topic :: Software Development :: Libraries
Classifier: Topic :: Utilities
Classifier: Environment :: Web Environment
Classifier: Framework :: Django
